Metadata-Version: 1.1
Name: flaimapper
Version: 2.3.3
Summary: Fragment Location Annotation Identification Mapper
Home-page: https://github.com/yhoogstrate/flaimapper
Author: Youri Hoogstrate
Author-email: not-for@public.use
License: UNKNOWN
Platform: UNKNOWN
Classifier: Environment :: Console
Classifier: Intended Audience :: Science/Research
Classifier: License :: OSI Approved :: GNU General Public License v3 (GPLv3)
Classifier: Operating System :: OS Independent
Classifier: Topic :: Scientific/Engineering
Classifier: Topic :: Scientific/Engineering :: Bio-Informatics
